LICENSE
MANIFEST.in
README.md
sbucket.py
setup.py
sbucket.egg-info/PKG-INFO
sbucket.egg-info/SOURCES.txt
sbucket.egg-info/dependency_links.txt
sbucket.egg-info/entry_points.txt
sbucket.egg-info/requires.txt
sbucket.egg-info/top_level.txt