Metadata-Version: 1.1
Name: sbucket
Version: 0.1.4
Summary: Spatial Bucketing of RIPE Atlas Probes on Map Projections.
Home-page: https://github.com/cod3monk/RIPE-Atlas-sbucket
Author: Julian Hammer
Author-email: julian.hammer@fau.de
License: AGPLv3
Platform: UNKNOWN
Classifier: Development Status :: 4 - Beta
Classifier: Intended Audience :: Developers
Classifier: Intended Audience :: Science/Research
Classifier: Intended Audience :: Information Technology
Classifier: Intended Audience :: System Administrators
Classifier: Intended Audience :: Telecommunications Industry
Classifier: Topic :: Utilities
Classifier: Topic :: Internet
Classifier: Environment :: Console
Classifier: Operating System :: POSIX
Classifier: Operating System :: MacOS
Classifier: Operating System :: Unix
Classifier: License :: OSI Approved :: GNU Affero General Public License v3
Classifier: Programming Language :: Python :: 2
Classifier: Programming Language :: Python :: 2.7
Classifier: Programming Language :: Python :: 3
Classifier: Programming Language :: Python :: 3.4
